fisbar/__init__.py
fisbar/__main__.py
fisbar/fisbar.py
fisbar/tables.py
fisbar-20210110.dist-info/AUTHORS
fisbar-20210110.dist-info/LICENSE
fisbar-20210110.dist-info/METADATA
fisbar-20210110.dist-info/WHEEL
fisbar-20210110.dist-info/top_level.txt
fisbar-20210110.dist-info/RECORD
