Metadata-Version: 2.1
Name: fisbar
Version: 20210110
Summary: Python implementation of BARFIT routine by A Sierk
Home-page: https://gitlab.in2p3.fr/gregoire.henning/fisbar-python
Author: Greg Henning
Author-email: ghenning@iphc.cnrs.fr
License: UNKNOWN
Platform: UNKNOWN
Classifier: Programming Language :: Python :: 3
Classifier: License :: OSI Approved :: CEA CNRS Inria Logiciel Libre License, version 2.1 (CeCILL-2.1)
Classifier: Operating System :: OS Independent
Requires-Python: >=3.6
Requires-Dist: numpy
